t00/SRLatch.v
module SRLatch_m(

	input  wire R		,
	input  wire S		,

	output wire OUT		,
	output wire XOUT
	
);

	assign OUT  = ~R && (S || OUT);
	assign XOUT = ~S && (R || XOUT);

endmodule

t00/DLatch.v
`include "SRLatch.v"

module DLatch_m(

	input  wire D		,
	input  wire E		,

	output wire OUT		,
	output wire XOUT

);

	wire srLatchS;
	wire srLatchR;


	assign srLatchS = D && E;
	assign srLatchR =~D && E;

	SRLatch_m SRLatch (.R (srLatchR), .S (srLatchS), .OUT (OUT), .XOUT(XOUT));	

endmodule

t00/DFF.v
`include "DLatch.v"

module DFlipFlop_m(

	input  wire E		,
	input  wire D		,

	output wire OUT		,
	output wire XOUT

);
	
	wire masterE;
	wire masterOut;

	assign masterE = ~E;


	DLatch_m Master (.E (masterE), .D (D        ), .OUT (masterOut));
	DLatch_m Slave  (.E (E      ), .D (masterOut), .OUT (OUT), .XOUT(XOUT));

endmodule

t00/testbench.v
`include "DFF.v"
`timescale 1ns / 10ps

module testbench ();

	reg clk = 1'b0;
	reg signal = 1'b1;

	always begin
		#1 clk = ~clk;
	end

	always begin
		#3.1415926535 signal = ~signal;
	end

	wire out;
	wire xout;

	DFlipFlop_m DFF(.D (signal), .E (clk), .OUT (out), .XOUT (xout));

	initial begin

		$dumpvars;
		$display ("Testing...");
		#200 $finish;

	end

endmodule

lab00/dump.vcd
$date
	Tue Feb 23 12:13:49 2021
$end
$version
	Icarus Verilog
$end
$timescale
	10ps
$end
$scope module testbench $end
$var wire 1 ! xout $end
$var wire 1 " out $end
$var reg 1 # clk $end
$var reg 1 $ signal $end
$scope module DFF $end
$var wire 1 $ D $end
$var wire 1 # E $end
$var wire 1 % masterE $end
$var wire 1 & masterOut $end
$var wire 1 ! XOUT $end
$var wire 1 " OUT $end
$scope module Master $end
$var wire 1 $ D $end
$var wire 1 % E $end
$var wire 1 ' srLatchR $end
$var wire 1 ( srLatchS $end
$var wire 1 ) XOUT $end
$var wire 1 & OUT $end
$scope module SRLatch $end
$var wire 1 & OUT $end
$var wire 1 ' R $end
$var wire 1 ( S $end
$var wire 1 ) XOUT $end
$upscope $end
$upscope $end
$scope module Slave $end
$var wire 1 & D $end
$var wire 1 # E $end
$var wire 1 * srLatchR $end
$var wire 1 + srLatchS $end
$var wire 1 ! XOUT $end
$var wire 1 " OUT $end
$scope module SRLatch $end
$var wire 1 " OUT $end
$var wire 1 * R $end
$var wire 1 + S $end
$var wire 1 ! XOUT $end
$upscope $end
$upscope $end
$upscope $end
$upscope $end
$enddefinitions $end
#0
$dumpvars
0+
0*
0)
1(
0'
1&
1%
1$
0#
x"
x!
$end
#100
1"
0!
0(
0%
1+
1#
#200
1(
1%
0+
0#
#300
0(
0%
1+
1#
#314
0$
#400
0&
1)
1'
1%
0+
0#
#500
0"
1!
0'
0%
1*
1#
#600
1'
1%
0*
0#
#628
1&
0)
0'
1(
1$
#700
1"
0!
0(
0%
1+
1#
#800
1(
1%
0+
0#
#900
0(
0%
1+
1#
#942
0$
#1000
0&
1)
1'
1%
0+
0#
#1100
0"
1!
0'
0%
1*
1#
#1200
1'
1%
0*
0#
#1256
1&
0)
0'
1(
1$
#1300
1"
0!
0(
0%
1+
1#
#1400
1(
1%
0+
0#
#1500
0(
0%
1+
1#
#1570
0$
#1600
0&
1)
1'
1%
0+
0#
#1700
0"
1!
0'
0%
1*
1#
#1800
1'
1%
0*
0#
#1884
1&
0)
0'
1(
1$
#1900
1"
0!
0(
0%
1+
1#
#2000
1(
1%
0+
0#
#2100
0(
0%
1+
1#
#2198
0$
#2200
0&
1)
1'
1%
0+
0#
#2300
0"
1!
0'
0%
1*
1#
#2400
1'
1%
0*
0#
#2500
0'
0%
1*
1#
#2512
1$
#2600
1&
0)
1(
1%
0*
0#
#2700
1"
0!
0(
0%
1+
1#
#2800
1(
1%
0+
0#
#2826
0&
1)
1'
0(
0$
#2900
0"
1!
0'
0%
1*
1#
#3000
1'
1%
0*
0#
#3100
0'
0%
1*
1#
#3140
1$
#3200
1&
0)
1(
1%
0*
0#
#3300
1"
0!
0(
0%
1+
1#
#3400
1(
1%
0+
0#
#3454
0&
1)
1'
0(
0$
#3500
0"
1!
0'
0%
1*
1#
#3600
1'
1%
0*
0#
#3700
0'
0%
1*
1#
#3768
1$
#3800
1&
0)
1(
1%
0*
0#
#3900
1"
0!
0(
0%
1+
1#
#4000
1(
1%
0+
0#
#4082
0&
1)
1'
0(
0$
#4100
0"
1!
0'
0%
1*
1#
#4200
1'
1%
0*
0#
#4300
0'
0%
1*
1#
#4396
1$
#4400
1&
0)
1(
1%
0*
0#
#4500
1"
0!
0(
0%
1+
1#
#4600
1(
1%
0+
0#
#4700
0(
0%
1+
1#
#4710
0$
#4800
0&
1)
1'
1%
0+
0#
#4900
0"
1!
0'
0%
1*
1#
#5000
1'
1%
0*
0#
#5024
1&
0)
0'
1(
1$
#5100
1"
0!
0(
0%
1+
1#
#5200
1(
1%
0+
0#
#5300
0(
0%
1+
1#
#5338
0$
#5400
0&
1)
1'
1%
0+
0#
#5500
0"
1!
0'
0%
1*
1#
#5600
1'
1%
0*
0#
#5652
1&
0)
0'
1(
1$
#5700
1"
0!
0(
0%
1+
1#
#5800
1(
1%
0+
0#
#5900
0(
0%
1+
1#
#5966
0$
#6000
0&
1)
1'
1%
0+
0#
#6100
0"
1!
0'
0%
1*
1#
#6200
1'
1%
0*
0#
#6280
1&
0)
0'
1(
1$
#6300
1"
0!
0(
0%
1+
1#
#6400
1(
1%
0+
0#
#6500
0(
0%
1+
1#
#6594
0$
#6600
0&
1)
1'
1%
0+
0#
#6700
0"
1!
0'
0%
1*
1#
#6800
1'
1%
0*
0#
#6900
0'
0%
1*
1#
#6908
1$
#7000
1&
0)
1(
1%
0*
0#
#7100
1"
0!
0(
0%
1+
1#
#7200
1(
1%
0+
0#
#7222
0&
1)
1'
0(
0$
#7300
0"
1!
0'
0%
1*
1#
#7400
1'
1%
0*
0#
#7500
0'
0%
1*
1#
#7536
1$
#7600
1&
0)
1(
1%
0*
0#
#7700
1"
0!
0(
0%
1+
1#
#7800
1(
1%
0+
0#
#7850
0&
1)
1'
0(
0$
#7900
0"
1!
0'
0%
1*
1#
#8000
1'
1%
0*
0#
#8100
0'
0%
1*
1#
#8164
1$
#8200
1&
0)
1(
1%
0*
0#
#8300
1"
0!
0(
0%
1+
1#
#8400
1(
1%
0+
0#
#8478
0&
1)
1'
0(
0$
#8500
0"
1!
0'
0%
1*
1#
#8600
1'
1%
0*
0#
#8700
0'
0%
1*
1#
#8792
1$
#8800
1&
0)
1(
1%
0*
0#
#8900
1"
0!
0(
0%
1+
1#
#9000
1(
1%
0+
0#
#9100
0(
0%
1+
1#
#9106
0$
#9200
0&
1)
1'
1%
0+
0#
#9300
0"
1!
0'
0%
1*
1#
#9400
1'
1%
0*
0#
#9420
1&
0)
0'
1(
1$
#9500
1"
0!
0(
0%
1+
1#
#9600
1(
1%
0+
0#
#9700
0(
0%
1+
1#
#9734
0$
#9800
0&
1)
1'
1%
0+
0#
#9900
0"
1!
0'
0%
1*
1#
#10000
1'
1%
0*
0#
#10048
1&
0)
0'
1(
1$
#10100
1"
0!
0(
0%
1+
1#
#10200
1(
1%
0+
0#
#10300
0(
0%
1+
1#
#10362
0$
#10400
0&
1)
1'
1%
0+
0#
#10500
0"
1!
0'
0%
1*
1#
#10600
1'
1%
0*
0#
#10676
1&
0)
0'
1(
1$
#10700
1"
0!
0(
0%
1+
1#
#10800
1(
1%
0+
0#
#10900
0(
0%
1+
1#
#10990
0$
#11000
0&
1)
1'
1%
0+
0#
#11100
0"
1!
0'
0%
1*
1#
#11200
1'
1%
0*
0#
#11300
0'
0%
1*
1#
#11304
1$
#11400
1&
0)
1(
1%
0*
0#
#11500
1"
0!
0(
0%
1+
1#
#11600
1(
1%
0+
0#
#11618
0&
1)
1'
0(
0$
#11700
0"
1!
0'
0%
1*
1#
#11800
1'
1%
0*
0#
#11900
0'
0%
1*
1#
#11932
1$
#12000
1&
0)
1(
1%
0*
0#
#12100
1"
0!
0(
0%
1+
1#
#12200
1(
1%
0+
0#
#12246
0&
1)
1'
0(
0$
#12300
0"
1!
0'
0%
1*
1#
#12400
1'
1%
0*
0#
#12500
0'
0%
1*
1#
#12560
1$
#12600
1&
0)
1(
1%
0*
0#
#12700
1"
0!
0(
0%
1+
1#
#12800
1(
1%
0+
0#
#12874
0&
1)
1'
0(
0$
#12900
0"
1!
0'
0%
1*
1#
#13000
1'
1%
0*
0#
#13100
0'
0%
1*
1#
#13188
1$
#13200
1&
0)
1(
1%
0*
0#
#13300
1"
0!
0(
0%
1+
1#
#13400
1(
1%
0+
0#
#13500
0(
0%
1+
1#
#13502
0$
#13600
0&
1)
1'
1%
0+
0#
#13700
0"
1!
0'
0%
1*
1#
#13800
1'
1%
0*
0#
#13816
1&
0)
0'
1(
1$
#13900
1"
0!
0(
0%
1+
1#
#14000
1(
1%
0+
0#
#14100
0(
0%
1+
1#
#14130
0$
#14200
0&
1)
1'
1%
0+
0#
#14300
0"
1!
0'
0%
1*
1#
#14400
1'
1%
0*
0#
#14444
1&
0)
0'
1(
1$
#14500
1"
0!
0(
0%
1+
1#
#14600
1(
1%
0+
0#
#14700
0(
0%
1+
1#
#14758
0$
#14800
0&
1)
1'
1%
0+
0#
#14900
0"
1!
0'
0%
1*
1#
#15000
1'
1%
0*
0#
#15072
1&
0)
0'
1(
1$
#15100
1"
0!
0(
0%
1+
1#
#15200
1(
1%
0+
0#
#15300
0(
0%
1+
1#
#15386
0$
#15400
0&
1)
1'
1%
0+
0#
#15500
0"
1!
0'
0%
1*
1#
#15600
1'
1%
0*
0#
#15700
1"
0!
1+
1&
0)
0'
0%
0*
0(
1#
1$
#15800
1(
1%
0+
0#
#15900
0(
0%
1+
1#
#16000
1(
1%
0+
0#
#16014
0&
1)
1'
0(
0$
#16100
0"
1!
0'
0%
1*
1#
#16200
1'
1%
0*
0#
#16300
0'
0%
1*
1#
#16328
1$
#16400
1&
0)
1(
1%
0*
0#
#16500
1"
0!
0(
0%
1+
1#
#16600
1(
1%
0+
0#
#16642
0&
1)
1'
0(
0$
#16700
0"
1!
0'
0%
1*
1#
#16800
1'
1%
0*
0#
#16900
0'
0%
1*
1#
#16956
1$
#17000
1&
0)
1(
1%
0*
0#
#17100
1"
0!
0(
0%
1+
1#
#17200
1(
1%
0+
0#
#17270
0&
1)
1'
0(
0$
#17300
0"
1!
0'
0%
1*
1#
#17400
1'
1%
0*
0#
#17500
0'
0%
1*
1#
#17584
1$
#17600
1&
0)
1(
1%
0*
0#
#17700
1"
0!
0(
0%
1+
1#
#17800
1(
1%
0+
0#
#17898
0&
1)
1'
0(
0$
#17900
0"
1!
0'
0%
1*
1#
#18000
1'
1%
0*
0#
#18100
0'
0%
1*
1#
#18200
1'
1%
0*
0#
#18212
1&
0)
0'
1(
1$
#18300
1"
0!
0(
0%
1+
1#
#18400
1(
1%
0+
0#
#18500
0(
0%
1+
1#
#18526
0$
#18600
0&
1)
1'
1%
0+
0#
#18700
0"
1!
0'
0%
1*
1#
#18800
1'
1%
0*
0#
#18840
1&
0)
0'
1(
1$
#18900
1"
0!
0(
0%
1+
1#
#19000
1(
1%
0+
0#
#19100
0(
0%
1+
1#
#19154
0$
#19200
0&
1)
1'
1%
0+
0#
#19300
0"
1!
0'
0%
1*
1#
#19400
1'
1%
0*
0#
#19468
1&
0)
0'
1(
1$
#19500
1"
0!
0(
0%
1+
1#
#19600
1(
1%
0+
0#
#19700
0(
0%
1+
1#
#19782
0$
#19800
0&
1)
1'
1%
0+
0#
#19900
0"
1!
0'
0%
1*
1#
#20000
1'
1%
0*
0#
